JPSLUtils/__init__.py
JPSLUtils/utils.py
JPSLUtils/javascript/JPSLUtils.js
JPSLUtils-0.7.3.dist-info/METADATA
JPSLUtils-0.7.3.dist-info/WHEEL
JPSLUtils-0.7.3.dist-info/top_level.txt
JPSLUtils-0.7.3.dist-info/RECORD
