Metadata-Version: 2.1
Name: JPSLUtils
Version: 0.7.3
Summary: Utilities for Jupyter Physical Science Lab project
Home-page: https://github.com/JupyterPhysSciLab/JPSLUtils
Author: Jonathan Gutow
Author-email: gutow@uwosh.edu
License: GPL-3.0+
Classifier: Development Status :: 4 - Beta
Classifier: Intended Audience :: Developers
Classifier: Intended Audience :: Education
Classifier: License :: OSI Approved :: GNU General Public License v3 or later (GPLv3+)
Classifier: Programming Language :: Python :: 3
Classifier: Programming Language :: JavaScript
Classifier: Operating System :: OS Independent
Requires-Dist: jupyter (>=1.0.0)
Requires-Dist: JPSLMenus
